deltalake/__init__.py
deltalake/deltatable.py
deltalake/schema.py
delta_lake_reader-0.2.16.dist-info/LICENSE.txt
delta_lake_reader-0.2.16.dist-info/METADATA
delta_lake_reader-0.2.16.dist-info/WHEEL
delta_lake_reader-0.2.16.dist-info/RECORD
