Metadata-Version: 2.1
Name: delta-lake-reader
Version: 0.2.16
Summary: Lightweight wrapper for reading Delta tables without Spark
Home-page: https://github.com/jeppe742/DeltaLakeReader
License: Apache-2.0
Author: Jeppe Johan Waarkjær Olsen
Author-email: jeppe742@gmail.com
Requires-Python: >=3.8,<4.0
Classifier: License :: OSI Approved :: Apache Software License
Classifier: Programming Language :: Python :: 3
Classifier: Programming Language :: Python :: 3.8
Classifier: Programming Language :: Python :: 3.9
Classifier: Programming Language :: Python :: 3.10
Classifier: Programming Language :: Python :: 3.11
Classifier: Programming Language :: Python :: 3.12
Provides-Extra: aws
Provides-Extra: azure
Provides-Extra: gcp
Requires-Dist: adlfs (>=2023,<2024) ; extra == "azure"
Requires-Dist: aiohttp (>=3.7.3,<4.0.0) ; extra == "azure"
Requires-Dist: fsspec (>=2023,<2024)
Requires-Dist: gcsfs (>=2023,<2024) ; extra == "gcp"
Requires-Dist: pandas (>=1.3.1,<2.0.0)
Requires-Dist: pyarrow (>=14.0.0,<15.0.0)
Requires-Dist: s3fs (>=2023,<2024) ; extra == "aws"
Project-URL: Repository, https://github.com/jeppe742/DeltaLakeReader
